bears/Constants.py
bears/VERSION
bears/__init__.py
bears/generate_package.py
bears/c_languages/CPPCheckBear.py
bears/c_languages/CPPCleanBear.py
bears/c_languages/CPPLintBear.py
bears/c_languages/CSecurityBear.py
bears/c_languages/CSharpLintBear.py
bears/c_languages/ClangBear.py
bears/c_languages/ClangComplexityBear.py
bears/c_languages/GNUIndentBear.py
bears/c_languages/__init__.py
bears/c_languages/codeclone_detection/ClangASTPrintBear.py
bears/c_languages/codeclone_detection/ClangCloneDetectionBear.py
bears/c_languages/codeclone_detection/ClangCountVectorCreator.py
bears/c_languages/codeclone_detection/ClangCountingConditions.py
bears/c_languages/codeclone_detection/ClangFunctionDifferenceBear.py
bears/c_languages/codeclone_detection/CloneDetectionRoutines.py
bears/c_languages/codeclone_detection/CountVector.py
bears/c_languages/codeclone_detection/__init__.py
bears/cmake/CMakeLintBear.py
bears/cmake/__init__.py
bears/coffee_script/CoffeeLintBear.py
bears/coffee_script/__init__.py
bears/configfiles/DockerfileLintBear.py
bears/configfiles/PuppetLintBear.py
bears/configfiles/__init__.py
bears/css/CSSAutoPrefixBear.py
bears/css/CSSLintBear.py
bears/css/StyleLintBear.py
bears/css/__init__.py
bears/csv/CSVLintBear.py
bears/csv/__init__.py
bears/dart/DartLintBear.py
bears/dart/__init__.py
bears/elm/ElmLintBear.py
bears/elm/__init__.py
bears/general/AnnotationBear.py
bears/general/CPDBear.py
bears/general/DuplicateFileBear.py
bears/general/FilenameBear.py
bears/general/IndentationBear.py
bears/general/InvalidLinkBear.py
bears/general/KeywordBear.py
bears/general/LicenseCheckBear.py
bears/general/LineCountBear.py
bears/general/LineLengthBear.py
bears/general/QuotesBear.py
bears/general/SpaceConsistencyBear.py
bears/general/__init__.py
bears/general/coalaBear.py
bears/gettext/DennisBear.py
bears/gettext/__init__.py
bears/go/GoErrCheckBear.py
bears/go/GoImportsBear.py
bears/go/GoLintBear.py
coala_bears-0.11.1.dist-info/DESCRIPTION.rst
coala_bears-0.11.1.dist-info/METADATA
coala_bears-0.11.1.dist-info/RECORD
coala_bears-0.11.1.dist-info/WHEEL
coala_bears-0.11.1.dist-info/entry_points.txt
coala_bears-0.11.1.dist-info/metadata.json
coala_bears-0.11.1.dist-info/top_level.txt
