Metadata-Version: 2.0
Name: coala-bears
Version: 0.11.1
Summary: Bears for coala (Code Analysis Application)
Home-page: http://coala.rtfd.org/
Author: Lasse Schuirmann, Fabian Neuschmidt, Mischa Krüger
Author-email: lasse.schuirmann@gmail.com, fabian@neuschmidt.de, makman@alice.de
License: AGPL-3.0
Platform: any
Classifier: Development Status :: 4 - Beta
Classifier: Environment :: Plugins
Classifier: Environment :: MacOS X
Classifier: Environment :: Win32 (MS Windows)
Classifier: Environment :: X11 Applications :: Gnome
Classifier: Intended Audience :: Science/Research
Classifier: Intended Audience :: Developers
Classifier: License :: OSI Approved :: GNU Affero General Public License v3 or later (AGPLv3+)
Classifier: Operating System :: OS Independent
Classifier: Programming Language :: Python :: Implementation :: CPython
Classifier: Programming Language :: Python :: 3.4
Classifier: Programming Language :: Python :: 3.5
Classifier: Programming Language :: Python :: 3 :: Only
Classifier: Topic :: Scientific/Engineering :: Information Analysis
Classifier: Topic :: Software Development :: Quality Assurance
Classifier: Topic :: Text Processing :: Linguistic
Requires-Dist: coala (~=0.11.0)
Requires-Dist: autoflake (~=0.6.6)
Requires-Dist: autopep8 (~=1.2)
Requires-Dist: bandit (~=1.2)
Requires-Dist: click (==6.6)
Requires-Dist: cmakelint (~=1.3)
Requires-Dist: cppclean (~=0.12.0)
Requires-Dist: cpplint (~=1.3)
Requires-Dist: dennis (~=0.8)
Requires-Dist: eradicate (~=0.1.6)
Requires-Dist: guess-language-spirit (~=0.5.2)
Requires-Dist: html-linter (~=0.3.0)
Requires-Dist: isort (~=4.2)
Requires-Dist: munkres3 (~=1.0)
Requires-Dist: mypy-lang (~=0.4.6)
Requires-Dist: nbformat (~=4.1)
Requires-Dist: nltk (~=3.2)
Requires-Dist: proselint (~=0.7.0)
Requires-Dist: pycodestyle (~=2.2)
Requires-Dist: pydocstyle (~=1.1)
Requires-Dist: pyflakes (~=1.4.0)
Requires-Dist: pylint (~=1.6)
Requires-Dist: pyroma (~=2.2.0)
Requires-Dist: pyyaml (~=3.12)
Requires-Dist: radon (==1.4.0)
Requires-Dist: restructuredtext-lint (~=1.0.0)
Requires-Dist: rstcheck (~=2.2)
Requires-Dist: safety (~=0.5.1)
Requires-Dist: scspell3k (~=2.0)
Requires-Dist: vulture (~=0.10.0)
Requires-Dist: yamllint (~=1.6.1)
Requires-Dist: yapf (~=0.14.0)
Provides-Extra: alldeps
Requires-Dist: autoflake (~=0.6.6); extra == 'alldeps'
Requires-Dist: autopep8 (~=1.2); extra == 'alldeps'
Requires-Dist: bandit (~=1.2); extra == 'alldeps'
Requires-Dist: click (==6.6); extra == 'alldeps'
Requires-Dist: cmakelint (~=1.3); extra == 'alldeps'
Requires-Dist: cppclean (~=0.12.0); extra == 'alldeps'
Requires-Dist: cpplint (~=1.3); extra == 'alldeps'
Requires-Dist: dennis (~=0.8); extra == 'alldeps'
Requires-Dist: eradicate (~=0.1.6); extra == 'alldeps'
Requires-Dist: guess-language-spirit (~=0.5.2); extra == 'alldeps'
Requires-Dist: html-linter (~=0.3.0); extra == 'alldeps'
Requires-Dist: isort (~=4.2); extra == 'alldeps'
Requires-Dist: language-check (~=1.0); extra == 'alldeps'
Requires-Dist: munkres3 (~=1.0); extra == 'alldeps'
Requires-Dist: mypy-lang (~=0.4.6); extra == 'alldeps'
Requires-Dist: nbformat (~=4.1); extra == 'alldeps'
Requires-Dist: nltk (~=3.2); extra == 'alldeps'
Requires-Dist: proselint (~=0.7.0); extra == 'alldeps'
Requires-Dist: pycodestyle (~=2.2); extra == 'alldeps'
Requires-Dist: pydocstyle (~=1.1); extra == 'alldeps'
Requires-Dist: pyflakes (~=1.4.0); extra == 'alldeps'
Requires-Dist: pylint (~=1.6); extra == 'alldeps'
Requires-Dist: pyroma (~=2.2.0); extra == 'alldeps'
Requires-Dist: pyyaml (~=3.12); extra == 'alldeps'
Requires-Dist: radon (==1.4.0); extra == 'alldeps'
Requires-Dist: restructuredtext-lint (~=1.0.0); extra == 'alldeps'
Requires-Dist: rstcheck (~=2.2); extra == 'alldeps'
Requires-Dist: safety (~=0.5.1); extra == 'alldeps'
Requires-Dist: scspell3k (~=2.0); extra == 'alldeps'
Requires-Dist: vulture (~=0.10.0); extra == 'alldeps'
Requires-Dist: yamllint (~=1.6.1); extra == 'alldeps'
Requires-Dist: yapf (~=0.14.0); extra == 'alldeps'
